cycle_prediction/__init__.py
cycle_prediction/t2e.py
cycle_prediction/weibull_utils.py
cycle_prediction-1.2.1.dist-info/LICENSE.txt
cycle_prediction-1.2.1.dist-info/METADATA
cycle_prediction-1.2.1.dist-info/WHEEL
cycle_prediction-1.2.1.dist-info/top_level.txt
cycle_prediction-1.2.1.dist-info/RECORD
