Metadata-Version: 2.1
Name: cycle-prediction
Version: 1.2.1
Summary: A package to train and predict the end of a process from        history logs
Home-page: https://github.com/fazaki/cycle_prediction/tree/master
Author: Fadi Baskharon
Author-email: nzfadi@gmail.com
License: UNKNOWN
Platform: UNKNOWN
Classifier: Programming Language :: Python :: 3.6
Classifier: License :: OSI Approved :: MIT License
Classifier: Operating System :: OS Independent
Requires-Python: >=3.6
Requires-Dist: tensorflow (==2.0.1)
Requires-Dist: Keras (==2.3.1)
Requires-Dist: Keras-Applications (==1.0.8)
Requires-Dist: Keras-Preprocessing (==1.1.0)
Requires-Dist: matplotlib (>=3.2.1)
Requires-Dist: numpy (>=1.18.2)
Requires-Dist: pandas (>=1.0.0)
Requires-Dist: scikit-learn (>=0.22.2.post1)
Requires-Dist: scipy (>=1.3.1)
Requires-Dist: seaborn (>=0.10.0)
Requires-Dist: wtte (>=1.1.1)
Provides-Extra: dev
Requires-Dist: pylint (==2.6.0) ; extra == 'dev'
Requires-Dist: twine (>=3.2.0) ; extra == 'dev'
Requires-Dist: pytest (==6.0.1) ; extra == 'dev'
Requires-Dist: pytest-docs (==0.1.0) ; extra == 'dev'
